cqt_rng/__init__.py
cqt_rng/base/__init__.py
cqt_rng/base/entropy_source.py
cqt_rng/base/post_processor.py
cqt_rng/base/rng.py
cqt_rng/entropy_sources/__init__.py
cqt_rng/entropy_sources/loader.py
cqt_rng/entropy_sources/real_devices/__init__.py
cqt_rng/entropy_sources/real_devices/borealis_sampler.py
cqt_rng/entropy_sources/real_devices/ibmq_sampler.py
cqt_rng/entropy_sources/simulators/__init__.py
cqt_rng/entropy_sources/simulators/boson_sampler.py
cqt_rng/entropy_sources/simulators/shisf_sampler.py
cqt_rng/entropy_sources/simulators/universal_qc_sampler.py
cqt_rng/post_processors/__init__.py
cqt_rng/post_processors/cqt_pp.py
cqt_rng/post_processors/no_postprocess.py
cqt_rng/post_processors/von_neumann_pp.py
cqt_rng/utils/__init__.py
cqt_rng/utils/generate_haar_unitary.py
cqt_rng/utils/utils.py
cqt_rng-0.0.2.dist-info/METADATA
cqt_rng-0.0.2.dist-info/WHEEL
cqt_rng-0.0.2.dist-info/top_level.txt
cqt_rng-0.0.2.dist-info/RECORD
