Metadata-Version: 2.1
Name: cqt-rng
Version: 0.0.2
Summary: A small package to generate random numbers using quantum entropy sources.
Author: 
Author-email: 
Keywords: rng,quantum
Classifier: Development Status :: 3 - Alpha
Classifier: Topic :: Scientific/Engineering :: Mathematics
Classifier: Programming Language :: Python :: 3.6
Classifier: Operating System :: OS Independent
Requires-Dist: qiskit
Requires-Dist: thewalrus
Requires-Dist: strawberryfields
Requires-Dist: numpy
Requires-Dist: scipy
Requires-Dist: matplotlib
Requires-Dist: tqdm
